devdeck_macos/__init__.py
devdeck_macos/assets/font-awesome/microphone-mute.png
devdeck_macos/assets/font-awesome/microphone.png
devdeck_macos/controls/__init__.py
devdeck_macos/controls/mic_mute_control.py
devdeck_macos-1.0.0.dist-info/LICENSE
devdeck_macos-1.0.0.dist-info/LICENSE.fork-original
devdeck_macos-1.0.0.dist-info/METADATA
devdeck_macos-1.0.0.dist-info/WHEEL
devdeck_macos-1.0.0.dist-info/top_level.txt
devdeck_macos-1.0.0.dist-info/RECORD
