Metadata-Version: 2.1
Name: devdeck-macos
Version: 1.0.0
Summary: DevDeck commands for interacting with a macOS system
Home-page: https://github.com/marcus-crane/devdeck-macos
Author: Marcus Crane
Author-email: marcus@utf9k.net
License: MIT
Platform: UNKNOWN
Requires-Dist: assertpy
Requires-Dist: devdeck-core (==1.0.7)
Requires-Dist: pytest
Requires-Dist: osascript (==2020.12.3)
Requires-Dist: parsedatetime
Requires-Dist: tzlocal
